odoo10_addon_crm_mailchimp-10.0.1.0.0.99.dev4-py3.8-nspkg.pth
odoo/addons/crm_mailchimp/README.rst
odoo/addons/crm_mailchimp/__init__.py
odoo/addons/crm_mailchimp/__manifest__.py
odoo/addons/crm_mailchimp/controllers/__init__.py
odoo/addons/crm_mailchimp/controllers/main.py
odoo/addons/crm_mailchimp/data/ir_cron.xml
odoo/addons/crm_mailchimp/demo/mailchimp_interest.xml
odoo/addons/crm_mailchimp/demo/mailchimp_interest_category.xml
odoo/addons/crm_mailchimp/demo/mailchimp_list.xml
odoo/addons/crm_mailchimp/demo/res_partner.xml
odoo/addons/crm_mailchimp/demo/res_users.xml
odoo/addons/crm_mailchimp/i18n/crm_mailchimp.pot
odoo/addons/crm_mailchimp/models/__init__.py
odoo/addons/crm_mailchimp/models/mailchimp_interest.py
odoo/addons/crm_mailchimp/models/mailchimp_interest_category.py
odoo/addons/crm_mailchimp/models/mailchimp_list.py
odoo/addons/crm_mailchimp/models/mailchimp_merge_field.py
odoo/addons/crm_mailchimp/models/mailchimp_settings.py
odoo/addons/crm_mailchimp/models/res_partner.py
odoo/addons/crm_mailchimp/readme/CONFIGURE.rst
odoo/addons/crm_mailchimp/readme/CONTRIBUTORS.rst
odoo/addons/crm_mailchimp/readme/CREDITS.rst
odoo/addons/crm_mailchimp/readme/DESCRIPTION.rst
odoo/addons/crm_mailchimp/readme/ROADMAP.rst
odoo/addons/crm_mailchimp/readme/USAGE.rst
odoo/addons/crm_mailchimp/security/ir.model.access.csv
odoo/addons/crm_mailchimp/security/ir_rule.xml
odoo/addons/crm_mailchimp/security/res_groups.xml
odoo/addons/crm_mailchimp/static/description/icon.png
odoo/addons/crm_mailchimp/static/description/index.html
odoo/addons/crm_mailchimp/tests/__init__.py
odoo/addons/crm_mailchimp/tests/test_crm_mailchimp.py
odoo/addons/crm_mailchimp/views/mailchimp_interest_category.xml
odoo/addons/crm_mailchimp/views/mailchimp_list.xml
odoo/addons/crm_mailchimp/views/mailchimp_merge_field.xml
odoo/addons/crm_mailchimp/views/mailchimp_settings.xml
odoo/addons/crm_mailchimp/views/menu.xml
odoo/addons/crm_mailchimp/views/res_partner.xml
odoo10_addon_crm_mailchimp-10.0.1.0.0.99.dev4.dist-info/METADATA
odoo10_addon_crm_mailchimp-10.0.1.0.0.99.dev4.dist-info/WHEEL
odoo10_addon_crm_mailchimp-10.0.1.0.0.99.dev4.dist-info/namespace_packages.txt
odoo10_addon_crm_mailchimp-10.0.1.0.0.99.dev4.dist-info/top_level.txt
odoo10_addon_crm_mailchimp-10.0.1.0.0.99.dev4.dist-info/RECORD
